deepanalysts/__init__.py
deepanalysts/backends/__init__.py
deepanalysts/backends/basement.py
deepanalysts/backends/composite.py
deepanalysts/backends/filesystem.py
deepanalysts/backends/protocol.py
deepanalysts/backends/sandbox.py
deepanalysts/backends/store.py
deepanalysts/backends/utils.py
deepanalysts/clients/__init__.py
deepanalysts/clients/basement.py
deepanalysts/middleware/__init__.py
deepanalysts/middleware/_utils.py
deepanalysts/middleware/filesystem.py
deepanalysts/middleware/memory.py
deepanalysts/middleware/patch_tool_calls.py
deepanalysts/middleware/skills.py
deepanalysts/middleware/subagents.py
deepanalysts/middleware/summarization.py
deepanalysts/middleware/tool_errors.py
deepanalysts/utils/__init__.py
deepanalysts/utils/retry.py
deepanalysts-0.1.3.dist-info/METADATA
deepanalysts-0.1.3.dist-info/WHEEL
deepanalysts-0.1.3.dist-info/top_level.txt
deepanalysts-0.1.3.dist-info/RECORD
