Metadata-Version: 2.4
Name: deepanalysts
Version: 0.1.3
Summary: LangChain/LangGraph middleware for building AI agents with memory, skills, and filesystem support
Author-email: Ganchuluun Narantsatsralt <tsatsralt@swifttech.cloud>
License: MIT
Project-URL: Homepage, https://github.com/SKE-Labs/embient-cli
Project-URL: Documentation, https://github.com/SKE-Labs/embient-cli/tree/main/libs/deepanalysts
Project-URL: Repository, https://github.com/SKE-Labs/embient-cli.git
Project-URL: Issues, https://github.com/SKE-Labs/embient-cli/issues
Keywords: langchain,langgraph,agents,middleware,ai,trading
Classifier: Development Status :: 3 - Alpha
Classifier: Intended Audience :: Developers
Classifier: License :: OSI Approved :: MIT License
Classifier: Programming Language :: Python :: 3
Classifier: Programming Language :: Python :: 3.11
Classifier: Programming Language :: Python :: 3.12
Classifier: Topic :: Scientific/Engineering :: Artificial Intelligence
Requires-Python: <4.0,>=3.11
Requires-Dist: langchain<2.0.0,>=1.2.3
Requires-Dist: langgraph>=0.2.0
Requires-Dist: httpx>=0.28.0
Requires-Dist: pyyaml>=6.0
Requires-Dist: tenacity>=8.2.0
Requires-Dist: wcmatch>=8.5.0
Provides-Extra: postgres
Requires-Dist: langgraph-checkpoint-postgres>=2.0.0; extra == "postgres"
Requires-Dist: psycopg[binary,pool]>=3.2.0; extra == "postgres"
Provides-Extra: dev
Requires-Dist: pytest>=8.0.0; extra == "dev"
Requires-Dist: pytest-anyio>=0.0.0; extra == "dev"
Requires-Dist: anyio>=4.0.0; extra == "dev"
Requires-Dist: ruff>=0.8.0; extra == "dev"
